<GuiXml>
    <Controls>
        <Control name="FCPHeaderIcon_Template" virtual="true">
            <Dimensions x="26" y="26"/>
            <Controls>
                <Texture name="$(parent)Texture" textureFile="/esoui/art/icons/u26_unknown_antiquity_questionmark.dds" tier="HIGH" mouseEnabled="true">
                    <Anchor point="CENTER"/>
                    <Dimensions x="18" y="18"/>
                    <OnMouseUp></OnMouseUp>
                </Texture>
                <!-- <Backdrop name="$(parent)Backdrop" centerColor="4000FF00" edgeColor="00000000">
                    <AnchorFill/>
                </Backdrop> -->
            </Controls>
        </Control>
<!-- ======================================================================================================================= -->
        <TopLevelControl name="FilteredChatPanel" clampedToScreen="false" mouseEnabled="false" movable="false" hidden="false">
            <Dimensions x="530" y="700"/>
            <Anchor point="LEFT" relativeTo="GuiRoot" relativePoint="RIGHT" offsetX="-30" offsetY="-70"/>
            <Controls>
                <Control name="$(parent)Sidebar" mouseEnabled="true">
                    <Dimensions x="30"/>
                    <Anchor point="TOPLEFT" relativeTo="$(parent)" relativePoint="TOPLEFT"/>
                    <Anchor point="BOTTOMLEFT" relativeTo="$(parent)" relativePoint="BOTTOMLEFT"/>
                    <Controls>
                        <Backdrop name="$(parent)Backdrop" centerColor="30000000" edgeColor="00000000">
                            <AnchorFill/>
                        </Backdrop>
                        <Label name="$(parent)Label" font="ZoFontGameBold" text="FCP" horizontalAlignment="LEFT">
                            <Dimensions x="400"/>
                            <Anchor point="TOP" relativeTo="$(parent)" relativePoint="TOP" offsetY="0"/>
                            <OnInitialized>
                                self:SetTransformRotationZ(math.rad(90))
                            </OnInitialized>
                        </Label>
                    </Controls>
                    <OnMouseUp>
                        LibFilteredChatPanel.OnSidebarClicked()
                    </OnMouseUp>
                </Control>
                <Control name="$(parent)Content">
                    <Anchor point="TOPLEFT" relativeTo="$(parent)Sidebar" relativePoint="TOPRIGHT" offsetX="4"/>
                    <Anchor point="BOTTOMRIGHT" relativeTo="$(parent)" relativePoint="BOTTOMRIGHT"/>
                    <Controls>
                        <Control name="$(parent)Header">
                            <Dimensions y="40"/>
                            <Anchor point="TOPLEFT" relativeTo="$(parent)" relativePoint="TOPLEFT"/>
                            <Anchor point="TOPRIGHT" relativeTo="$(parent)" relativePoint="TOPRIGHT"/>
                            <Controls>
                                <Backdrop name="$(parent)Divider" centerColor="75000000" edgeColor="00000000">
                                    <Dimensions y="2"/>
                                    <Anchor point="BOTTOMLEFT" offsetY="-4"/>
                                    <Anchor point="BOTTOMRIGHT" offsetY="-4"/>
                                </Backdrop>
                            </Controls>
                        </Control>
                        <Control name="$(parent)Footer">
                            <Dimensions y="30"/>
                            <Anchor point="BOTTOMLEFT" relativeTo="$(parent)" relativePoint="BOTTOMLEFT"/>
                            <Anchor point="BOTTOMRIGHT" relativeTo="$(parent)" relativePoint="BOTTOMRIGHT"/>
                            <Controls>
                                <!-- <Backdrop name="$(parent)Backdrop" centerColor="75000000" edgeColor="00000000">
                                    <AnchorFill/>
                                </Backdrop> -->
                            </Controls>
                        </Control>
<!-- ======================================================================================================================= -->
                        <TextBuffer name="$(parent)Buffer" font="ZoFontGameSmall" linkEnabled="false" mouseEnabled="true">
                            <Anchor point="TOPLEFT" relativeTo="$(parent)Header" relativePoint="BOTTOMLEFT"/>
                            <Anchor point="BOTTOMRIGHT" relativeTo="$(parent)Footer" relativePoint="TOPRIGHT" offsetX="-16"/>
                        </TextBuffer>
                        
                        <Slider name="$(parent)Slider" mouseEnabled="true" step="1">
                            <Anchor point="TOPLEFT" relativePoint="TOPRIGHT" relativeTo="$(parent)Buffer" offsetX="0" offsetY="12"/>
                            <Anchor point="BOTTOMLEFT" relativePoint="BOTTOMRIGHT" relativeTo="$(parent)Buffer" offsetX="0" offsetY="-24"/>
                            <Dimensions x="8"/>
                            <Limits min="1" max="1"/>
                            
                            <ThumbTexture
                                textureFile="EsoUI/Art/ChatWindow/chat_thumb.dds"
                                disabledTextureFile="EsoUI/Art/ChatWindow/chat_thumb_disabled.dds"
                                thumbWidth="8"
                                thumbHeight="22"
                                bottom="0.6875"
                            />
                            
                            <BackgroundMiddle textureFile="EsoUI/Art/ChatWindow/chat_scrollbar_track.dds"/>
                            
                            <Controls>
                                <Button name="$(parent)ScrollUp" inherits="ZO_ScrollUpButton">
                                    <Anchor point="BOTTOM" relativePoint="TOP" offsetX="-1"/>
                                    <Dimensions x="12" y="12"/>
                                    <Textures
                                        normal="EsoUI/Art/ChatWindow/chat_scrollbar_upArrow_up.dds"
                                        pressed="EsoUI/Art/ChatWindow/chat_scrollbar_upArrow_down.dds"
                                        mouseOver="EsoUI/Art/ChatWindow/chat_scrollbar_upArrow_over.dds"
                                        disabled="EsoUI/Art/ChatWindow/chat_scrollbar_upArrow_disabled.dds"
                                    />
                                </Button>
                                
                                <Button name="$(parent)ScrollDown" inherits="ZO_ScrollDownButton">
                                    <Anchor point="TOP" relativePoint="BOTTOM" offsetX="-1"/>
                                    <Dimensions x="12" y="12"/>
                                    <Textures
                                        normal="EsoUI/Art/ChatWindow/chat_scrollbar_downArrow_up.dds"
                                        pressed="EsoUI/Art/ChatWindow/chat_scrollbar_downArrow_down.dds"
                                        mouseOver="EsoUI/Art/ChatWindow/chat_scrollbar_downArrow_over.dds"
                                        disabled="EsoUI/Art/ChatWindow/chat_scrollbar_downArrow_disabled.dds"
                                    />
                                </Button>
                                
                                <Button name="$(parent)ScrollEnd" inherits="ZO_ScrollEndButton">
                                    <Anchor point="TOP" relativePoint="BOTTOM" relativeTo="$(parent)ScrollDown"/>
                                    <Dimensions x="12" y="12"/>                                         
                                </Button>                                               
                            </Controls>
                        </Slider>                                   
<!-- ======================================================================================================================= -->
                    </Controls>
                </Control>
                <Backdrop name="$(parent)Backdrop" centerColor="40000000" edgeColor="00000000">
                    <AnchorFill/>
                </Backdrop>
            </Controls>
        </TopLevelControl>

    </Controls>
</GuiXml>
